docs/source/conf.py
epicallypowerful/__init__.py
epicallypowerful/actuation/__init__.py
epicallypowerful/actuation/actuator_abc.py
epicallypowerful/actuation/actuator_group.py
epicallypowerful/actuation/motor_data.py
epicallypowerful/actuation/torque_monitor.py
epicallypowerful/actuation/cubemars/__init__.py
epicallypowerful/actuation/cubemars/cubemars.py
epicallypowerful/actuation/cubemars/cubemars_driver.py
epicallypowerful/actuation/cubemars/cubemars_servo.py
epicallypowerful/actuation/cubemars/cubemars_v3.py
epicallypowerful/actuation/cybergear/__init__.py
epicallypowerful/actuation/cybergear/cybergear.py
epicallypowerful/actuation/robstride/__init__.py
epicallypowerful/actuation/robstride/robstride.py
epicallypowerful/actuation/robstride/robstride_driver.py
epicallypowerful/sensing/__init__.py
epicallypowerful/sensing/imu_abc.py
epicallypowerful/sensing/imu_data.py
epicallypowerful/sensing/microstrain/microstrain_imu.py
epicallypowerful/sensing/mpu9250/calibrate_mpu9250.py
epicallypowerful/sensing/mpu9250/mpu9250_imu.py
epicallypowerful/sensing/open_imu/__init__.py
epicallypowerful/sensing/open_imu/open_imu.py
epicallypowerful/sensing/open_imu/range_converter.py
epicallypowerful/sensing/open_imu/sae_j1939.py
epicallypowerful/toolbox/__init__.py
epicallypowerful/toolbox/_clocking.cpython-311-x86_64-linux-musl.so
epicallypowerful/toolbox/_clocking.pyx
epicallypowerful/toolbox/cli.py
epicallypowerful/toolbox/clocking.py
epicallypowerful/toolbox/data_recorder.py
epicallypowerful/toolbox/jetson_performance.py
epicallypowerful/toolbox/robstride_setup.py
epicallypowerful/toolbox/robstride_setup_gui.py
epicallypowerful/toolbox/visualization.py
examples/display_actuator_data.py
examples/display_microstrain_imu_data.py
examples/display_mpu9250_imu_data.py
examples/display_open_imu_data.py
examples/impedance_controller.py
examples/imu_actuator_controller.py
examples/position_controller.py
epicallypowerful-1.0.3.dist-info/METADATA
epicallypowerful-1.0.3.dist-info/WHEEL
epicallypowerful-1.0.3.dist-info/entry_points.txt
epicallypowerful-1.0.3.dist-info/top_level.txt
epicallypowerful-1.0.3.dist-info/RECORD
epicallypowerful-1.0.3.dist-info/licenses/LICENSE
